kfp_command_line_tools/__init__.py
kfp_command_line_tools/utils.py
kfp_command_line_tools/experiment/__init__.py
kfp_command_line_tools/experiment/experiment_commands.py
kfp_command_line_tools/experiment/experiment_main.py
kfp_command_line_tools/pipeline/__init__.py
kfp_command_line_tools/pipeline/pipeline_commands.py
kfp_command_line_tools/pipeline/pipeline_main.py
kfp_command_line_tools/read_config/__init__.py
kfp_command_line_tools/read_config/config_file.py
kfp_command_line_tools/run/__init__.py
kfp_command_line_tools/run/run_command.py
kfp_command_line_tools/run/run_main.py
kfp_command_line_tools/test/__init__.py
kfp_command_line_tools/test/read_config/__init__.py
kfp_command_line_tools-0.1.0.dist-info/DESCRIPTION.rst
kfp_command_line_tools-0.1.0.dist-info/LICENSE.txt
kfp_command_line_tools-0.1.0.dist-info/METADATA
kfp_command_line_tools-0.1.0.dist-info/RECORD
kfp_command_line_tools-0.1.0.dist-info/WHEEL
kfp_command_line_tools-0.1.0.dist-info/entry_points.txt
kfp_command_line_tools-0.1.0.dist-info/metadata.json
kfp_command_line_tools-0.1.0.dist-info/top_level.txt
